accinv/__init__.py
accinv/__main__.py
accinv/degeneracy.py
accinv/jacobian.py
accinv/loco.py
accinv/model.py
accinv/optim.py
accinv/parameters.py
accinv/utils.py
accinv-0.1.0.post1.dist-info/METADATA
accinv-0.1.0.post1.dist-info/WHEEL
accinv-0.1.0.post1.dist-info/top_level.txt
accinv-0.1.0.post1.dist-info/RECORD
