Metadata-Version: 2.1
Name: accinv
Version: 0.1.0.post1
Summary: Python project for inverse modeling of accelerator lattices
Author: Dominik Vilsmeier
Author-email: d.vilsmeier@gsi.de
License: GNU General Public License 3
Project-URL: Documentation, https://accinv.readthedocs.io/
Project-URL: Code, https://gitlab.com/Dominik1123/accinv
Project-URL: Issue tracker, https://gitlab.com/Dominik1123/accinv/-/issues
Project-URL: Changelog, https://accinv.readthedocs.io/en/latest/changelog/changelog.html
Keywords: inverse,modeling,accelerator,lattice,linear-optics-from-closed-orbits,loco,orbit-response-matrix,orm
Classifier: Development Status :: 4 - Beta
Classifier: Intended Audience :: Science/Research
Classifier: Topic :: Scientific/Engineering :: Physics
Classifier: Programming Language :: Python :: 3.9
Classifier: Programming Language :: Python :: 3.10
Classifier: Programming Language :: Python :: 3.11
Classifier: License :: OSI Approved :: GNU General Public License v3 or later (GPLv3+)
Requires-Dist: click
Requires-Dist: cpymad
Requires-Dist: numpy
Requires-Dist: scipy
Requires-Dist: typing-extensions (>=4.0.0)
Provides-Extra: develop
Requires-Dist: flake8 ; extra == 'develop'
Requires-Dist: mypy ; extra == 'develop'
Requires-Dist: pre-commit ; extra == 'develop'
Requires-Dist: reuse ; extra == 'develop'
Provides-Extra: docs
Requires-Dist: sphinx ; extra == 'docs'
Provides-Extra: tests
Requires-Dist: pytest ; extra == 'tests'
